.travis.yml
AUTHORS.txt
CHANGES.txt
CITATION.txt
COPYING.txt
MANIFEST.in
Makefile
README.rst
README.txt
_wormtablemodule.c
gtf2wt_dev.py
halffloat.c
halffloat.h
setup.py
tests.py
vcf2wt_dev.py
wtadmin_dev.py
docs/Makefile
docs/asy/Makefile
docs/asy/row-format.asy
docs/images/README
docs/paper/Makefile
docs/paper/bmc_article.bst
docs/paper/bmc_article.cls
docs/paper/paper.bib
docs/paper/paper.tex
docs/source/api.rst
docs/source/conf.py
docs/source/data-storage.rst
docs/source/index.rst
docs/source/introduction.rst
docs/source/performance.rst
docs/source/tutorial.rst
examples/build-pythons.py
examples/count-ts-tv-methods.py
examples/tutorial/count-ts-tv.py
examples/tutorial/find-hq-snps.py
examples/tutorial/sample.vcf
examples/vcf-utils/hq-snps-bygt.py
examples/vcf-utils/sliding-mean.py
examples/vcf-utils/snp-filter.py
scripts/gtf2wt
scripts/vcf2wt
scripts/wtadmin
scripts/wtadmin-completion.sh
test/__init__.py
test/highlevel.py
test/lowlevel.py
test/utilities.py
test/data/example.vcf
test/data/sample.vcf
test/data/sample_1.gtf
test/data/sample_2.gtf
wormtable/__init__.py
wormtable/cli.py
wormtable/gtf2wt.py
wormtable/tables.py
wormtable/vcf2wt.py
wormtable/wtadmin.py
wormtable.egg-info/PKG-INFO
wormtable.egg-info/SOURCES.txt
wormtable.egg-info/dependency_links.txt
wormtable.egg-info/top_level.txt