Metadata-Version: 2.1
Name: wormtable
Version: 0.1.6
Summary: Write-once read-many data sets using Berkeley DB.
Home-page: http://pypi.python.org/pypi/wormtable
Author: Jerome Kelleher, Dan Halligan, Rob Ness
Author-email: jerome.kelleher@ed.ac.uk
License: GNU LGPLv3+
Keywords: Berkeley DB,VCF,Variant Call Format,Bioinformatics
Platform: POSIX
Classifier: Programming Language :: C
Classifier: Programming Language :: Python
Classifier: Programming Language :: Python :: 3
Classifier: Programming Language :: Python :: 3.9
Classifier: Programming Language :: Python :: 3.10
Classifier: Programming Language :: Python :: 3.11
Classifier: Development Status :: 4 - Beta
Classifier: Environment :: Other Environment
Classifier: Intended Audience :: Science/Research
Classifier: License :: OSI Approved :: GNU Lesser General Public License v3 or later (LGPLv3+)
Classifier: Operating System :: POSIX
Classifier: Topic :: Scientific/Engineering
Classifier: Topic :: Scientific/Engineering :: Bio-Informatics
License-File: COPYING.txt
License-File: AUTHORS.txt
